dgps/__init__.py
dgps/utils/__init__.py
dgps_utils-0.1.7.dist-info/METADATA
dgps_utils-0.1.7.dist-info/WHEEL
dgps_utils-0.1.7.dist-info/top_level.txt
dgps_utils-0.1.7.dist-info/RECORD
